simple_discord/__init__.py
simple_discord/simple_discord.py
simple_discord/simple_discord.py.py
simple_discord-53.0.0.dist-info/LICENSE
simple_discord-53.0.0.dist-info/METADATA
simple_discord-53.0.0.dist-info/WHEEL
simple_discord-53.0.0.dist-info/top_level.txt
simple_discord-53.0.0.dist-info/RECORD
