Metadata-Version: 2.1
Name: simple-discord
Version: 53.0.0
Summary: Make Discord bots extremely easily
Home-page: https://github.com/TricolorHen061/simple-discord
Author: TricolorHen061
Author-email: thisisnotarealemailaddress@ndlnjkalbhddbagj.com
License: UNKNOWN
Project-URL: Bug Tracker, https://github.com/TricolorHen061/simple-discord/issues
Platform: UNKNOWN
Classifier: Programming Language :: Python :: 3
Classifier: License :: OSI Approved :: MIT License
Classifier: Operating System :: OS Independent
Requires-Python: >=3.6
License-File: LICENSE
